siege_utilities/__init__.py
siege_utilities/core/__init__.py
siege_utilities/core/logging.py
siege_utilities/core/string_utils.py
siege_utilities/distributed/__init__.py
siege_utilities/distributed/hdfs_config.py
siege_utilities/distributed/hdfs_legacy.py
siege_utilities/distributed/hdfs_operations.py
siege_utilities/distributed/spark_utils.py
siege_utilities/files/__init__.py
siege_utilities/files/hashing.py
siege_utilities/files/operations.py
siege_utilities/files/paths.py
siege_utilities/files/remote.py
siege_utilities/files/shell.py
siege_utilities/geo/__init__.py
siege_utilities/geo/geocoding.py
siege_utilities-1.0.0.dist-info/licenses/LICENSE
siege_utilities-1.0.0.dist-info/METADATA
siege_utilities-1.0.0.dist-info/WHEEL
siege_utilities-1.0.0.dist-info/top_level.txt
siege_utilities-1.0.0.dist-info/RECORD
